immpy/__init__.py
immpy/immpy.py
immpy-2.2.1.dist-info/LICENSE
immpy-2.2.1.dist-info/METADATA
immpy-2.2.1.dist-info/WHEEL
immpy-2.2.1.dist-info/top_level.txt
immpy-2.2.1.dist-info/RECORD
