Metadata-Version: 2.1
Name: immpy
Version: 2.2.1
Summary: A package for the management of patterns in indoor mobility data
Author: Ip2211po
Author-email: ip2211po@gmail.com
License: MIT
Classifier: License :: OSI Approved :: MIT License
Classifier: Programming Language :: Python :: 3
Classifier: Programming Language :: Python :: 3.7
License-File: LICENSE
Requires-Dist: pandas
Requires-Dist: prettytable
Requires-Dist: scipy
Requires-Dist: matplotlib
